pelak/__init__.py
pelak/assets.py
pelak/bekesh.py
pelak/data/Far_RoyaBd.ttf
pelak/data/ain.png
pelak/data/alef.png
pelak/data/gha.png
pelak/data/malul.png
pelak/data/police.png
pelak/data/sepah.png
pelak/data/taxi.png
pelak-0.1.0.dist-info/METADATA
pelak-0.1.0.dist-info/WHEEL
pelak-0.1.0.dist-info/top_level.txt
pelak-0.1.0.dist-info/RECORD
