Metadata-Version: 2.4
Name: pelak
Version: 0.1.0
Summary: (نسخه آزمايشي) تولید تصویر پلاک استاندارد ایرانی با پشتیبانی از قالب‌های خاص
Home-page: https://github.com/RezaGooner/pelak
Author: RezaGooner
Author-email: RezaAsadiProgrammer@Gmail.com
License: MIT
Classifier: Programming Language :: Python :: 3
Classifier: License :: OSI Approved :: MIT License
Classifier: Operating System :: OS Independent
Requires-Python: >=3.7
Requires-Dist: pillow>=10.0.0
Dynamic: author
Dynamic: author-email
Dynamic: classifier
Dynamic: description-content-type
Dynamic: home-page
Dynamic: license
Dynamic: requires-dist
Dynamic: requires-python
Dynamic: summary
